PyStemmusScope/__init__.py
PyStemmusScope/config_io.py
PyStemmusScope/forcing_io.py
PyStemmusScope/save.py
PyStemmusScope/soil_io.py
PyStemmusScope/stemmus_scope.py
PyStemmusScope/utils.py
PyStemmusScope/variable_conversion.py
PyStemmusScope/bmi/__init__.py
PyStemmusScope/bmi/docker_process.py
PyStemmusScope/bmi/docker_utils.py
PyStemmusScope/bmi/implementation.py
PyStemmusScope/bmi/local_process.py
PyStemmusScope/bmi/utils.py
PyStemmusScope/bmi/variable_reference.py
PyStemmusScope/global_data/__init__.py
PyStemmusScope/global_data/cams_co2.py
PyStemmusScope/global_data/cci_landcover.py
PyStemmusScope/global_data/copernicus_lai.py
PyStemmusScope/global_data/era5.py
PyStemmusScope/global_data/eth_canopy_height.py
PyStemmusScope/global_data/global_data_selection.py
PyStemmusScope/global_data/prism_dem.py
PyStemmusScope/global_data/utils.py
PyStemmusScope/global_data/assets/dem_filenames_compressed.txt.gz
PyStemmusScope/global_data/assets/h_canopy_filenames_compressed.txt.gz
PyStemmusScope/global_data/assets/lccs_to_igbp_table.csv
pystemmusscope-0.5.0.dist-info/METADATA
pystemmusscope-0.5.0.dist-info/WHEEL
pystemmusscope-0.5.0.dist-info/licenses/LICENSE
pystemmusscope-0.5.0.dist-info/RECORD
