Metadata-Version: 2.4
Name: PyStemmusScope
Version: 0.5.0
Summary: Python modules for running the STEMMUS-SCOPE model.
Author: Sarah Alidoost, Bart Schilperoort, Yang Liu
Author-email: f.alidoost@esciencecenter.nl
Maintainer-email: Sarah Alidoost <f.alidoost@esciencecenter.nl>, Yang Liu <y.liu@esciencecenter.nl>, Bart Schilperoort <b.schilperoort@esciencecenter.nl>
License-Expression: Apache-2.0
License-File: LICENSE
Keywords: STEMMUS-SCOPE,py
Classifier: Development Status :: 2 - Pre-Alpha
Classifier: Intended Audience :: Developers
Classifier: License :: OSI Approved :: Apache Software License
Classifier: Natural Language :: English
Classifier: Operating System :: OS Independent
Classifier: Programming Language :: Python
Classifier: Programming Language :: Python :: 3 :: Only
Classifier: Programming Language :: Python :: 3.9
Classifier: Programming Language :: Python :: 3.10
Classifier: Programming Language :: Python :: 3.11
Requires-Python: <3.12,>=3.9
Requires-Dist: bmipy
Requires-Dist: dask
Requires-Dist: h5py
Requires-Dist: hdf5storage
Requires-Dist: matplotlib
Requires-Dist: netcdf4==1.6.4
Requires-Dist: numpy<2
Requires-Dist: pandas<2
Requires-Dist: rioxarray
Requires-Dist: scipy
Requires-Dist: xarray
Provides-Extra: dev
Requires-Dist: black==23.12.1; extra == 'dev'
Requires-Dist: bump2version; extra == 'dev'
Requires-Dist: hatch; extra == 'dev'
Requires-Dist: isort; extra == 'dev'
Requires-Dist: mypy; extra == 'dev'
Requires-Dist: pytest; extra == 'dev'
Requires-Dist: pytest-cov; extra == 'dev'
Requires-Dist: ruff; extra == 'dev'
Requires-Dist: types-requests; extra == 'dev'
Provides-Extra: docker
Requires-Dist: docker; extra == 'docker'
Provides-Extra: docs
Requires-Dist: mkdocs; extra == 'docs'
Requires-Dist: mkdocs-gen-files; extra == 'docs'
Requires-Dist: mkdocs-jupyter; extra == 'docs'
Requires-Dist: mkdocs-material; extra == 'docs'
Requires-Dist: mkdocstrings[python]; extra == 'docs'
